{"label": "186102.a.558306.1", "conductor": 186102, "disc": 558306, "coeffs": [0, 12, 36, 8, -3, 2, 1], "pts": null, "count": null, "root": 0, "g": [[12, 36, 8, -3, 2, 1]], "x-coords": [], "verified": false, "hasse_principle": true, "obstruction_found": false, "search_bound": 100000, "twists": [{"coeffs": ["-36", "-105", "-25", "8", "-6", "-3"], "found_pts": 0, "base_pt": null, "loc_solv": false, "pts": [], "verified": true, "g1": [{"g": [12, 36, 8, -3, 2, 1], "aInv": null, "rank": null, "MW_proven": null, "gens": null, "gens_reduced": null}]}, {"coeffs": ["1"], "found_pts": 2, "base_pt": [0, 0, 0, 0, 1], "loc_solv": true, "pts": null, "verified": false, "g1": [{"g": [12, 36, 8, -3, 2, 1], "aInv": [["0", "0", "0", "0", "0"], ["15105", "39012", "-6210", "-1188", "3015"], ["0", "0", "0", "0", "0"], ["5420856", "13736550", "-2799735", "-77976", "956517"], ["-20406582576", "-52736032260", "8321791941", "1646328258", "-4088177487"]], "rank": null, "MW_proven": null, "gens": null, "gens_reduced": null}]}, {"coeffs": ["12", "35", "8", "-3", "2", "1"], "found_pts": 1, "base_pt": [1, 0, 0, 0, 0], "loc_solv": true, "pts": null, "verified": false, "g1": [{"g": [12, 36, 8, -3, 2, 1], "aInv": [["0", "0", "0", "0", "0"], ["9", "-4", "1", "0", "0"], ["0", "0", "0", "0", "0"], ["-104", "-50", "25", "-8", "-3"], ["96", "-64", "25", "-6", "1"]], "rank": null, "MW_proven": null, "gens": null, "gens_reduced": null}]}, {"coeffs": ["-3", "1", "1"], "found_pts": 1, "base_pt": [4, -9, 21, -51, 123], "loc_solv": true, "pts": null, "verified": false, "g1": [{"g": [12, 36, 8, -3, 2, 1], "aInv": [["0", "0", "0", "0", "0"], ["9", "23", "-2", "-1", "1"], ["0", "0", "0", "0", "0"], ["-200", "-662", "-343", "-52", "-3"], ["468", "2420", "3885", "2226", "413"]], "rank": null, "MW_proven": null, "gens": null, "gens_reduced": null}]}], "runtime": 12.044681072235107, "exception": false}