{"label": "60160.a.120320.1", "conductor": 60160, "disc": 120320, "coeffs": [0, 8, 12, -12, -16, 4, 5], "pts": null, "count": null, "root": 0, "g": [[-2, 0, 1], [-4, -6, 4, 5]], "x-coords": null, "verified": false, "hasse_principle": true, "obstruction_found": false, "twists": [{"coeffs": ["2", "3", "1"], "found_pts": 0, "base_pt": null, "loc_solv": false, "loc_solv_error": false, "pts": [], "verified": true, "g1": [{"g": [-2, 0, 1], "aInv": null, "rank": null, "MW_proven": null, "chabauty_possible": null, "chabauty_memory_error": false, "gens": null}, {"g": [-4, -6, 4, 5], "aInv": null, "rank": null, "MW_proven": null, "chabauty_possible": null, "chabauty_memory_error": false, "gens": null}]}, {"coeffs": ["-16", "-22", "29", "36", "-7", "-10"], "found_pts": 2, "base_pt": [9, -8, 8, -8, 8], "loc_solv": true, "loc_solv_error": false, "pts": null, "verified": false, "g1": [{"g": [-2, 0, 1], "aInv": [["0", "0"], ["4", "-2"], ["0", "0"], ["-36", "-26"], ["96", "68"]], "rank": 2, "MW_proven": true, "chabauty_possible": true, "chabauty_memory_error": false, "gens": [[["6", "4"], ["16", "12"], ["1", "0"]], [["3", "2"], ["1", "1"], ["1", "0"]]], "MW_orders": [0, 0], "gens_reduced": true}, {"g": [-4, -6, 4, 5], "aInv": [["0", "0", "0"], ["-6", "1", "20"], ["0", "0", "0"], ["160", "-74", "-555"], ["-780", "186", "2420"]], "rank": 2, "MW_proven": true, "chabauty_possible": true, "chabauty_memory_error": false, "gens": [[["-2", "3", "10"], ["0", "0", "0"], ["1", "0", "0"]], [["-6", "1", "20"], ["-44", "-10", "100"], ["1", "0", "0"]], [["-21/2", "-47/16", "745/32"], ["-1213/16", "-3323/64", "15355/128"], ["1", "0", "0"]]], "MW_orders": [2, 0, 0], "gens_reduced": true}]}, {"coeffs": ["16", "30", "-10", "-33", "-5", "5"], "found_pts": 0, "base_pt": null, "loc_solv": false, "loc_solv_error": false, "pts": [], "verified": true, "g1": [{"g": [-2, 0, 1], "aInv": null, "rank": null, "MW_proven": null, "chabauty_possible": null, "chabauty_memory_error": false, "gens": null}, {"g": [-4, -6, 4, 5], "aInv": null, "rank": null, "MW_proven": null, "chabauty_possible": null, "chabauty_memory_error": false, "gens": null}]}, {"coeffs": ["32", "492/5", "318/5", "-318/5", "-439/5", "-134/5"], "found_pts": 0, "base_pt": null, "loc_solv": false, "loc_solv_error": false, "pts": [], "verified": true, "g1": [{"g": [-2, 0, 1], "aInv": null, "rank": null, "MW_proven": null, "chabauty_possible": null, "chabauty_memory_error": false, "gens": null}, {"g": [-4, -6, 4, 5], "aInv": null, "rank": null, "MW_proven": null, "chabauty_possible": null, "chabauty_memory_error": false, "gens": null}]}, {"coeffs": ["-2", "4", "7", "-4", "-5"], "found_pts": 4, "base_pt": [9, -10, 10, -12, 12], "loc_solv": true, "loc_solv_error": false, "pts": null, "verified": false, "g1": [{"g": [-2, 0, 1], "aInv": [["0", "0"], ["2", "-2"], ["0", "0"], ["-18", "-13"], ["-34", "-24"]], "rank": 3, "MW_proven": true, "chabauty_possible": true, "chabauty_memory_error": false, "gens": [[["-1", "-1"], ["1", "0"], ["1", "0"]], [["4", "3"], ["-6", "-4"], ["1", "0"]], [["12", "8"], ["54", "37"], ["1", "0"]]], "MW_orders": [0, 0, 0], "gens_reduced": true}, {"g": [-4, -6, 4, 5], "aInv": [["0", "0", "0"], ["0", "-11", "-15/2"], ["0", "0", "0"], ["-134", "-344", "-385/2"], ["-638", "-1564", "-1685/2"]], "rank": 3, "MW_proven": true, "chabauty_possible": true, "chabauty_memory_error": false, "gens": [[["-4", "-7", "-5/2"], ["0", "0", "0"], ["1", "0", "0"]], [["-1", "-2", "-5/2"], ["-3", "-5", "0"], ["1", "0", "0"]], [["-3", "-17/4", "-5/8"], ["19/4", "25/2", "125/16"], ["1", "0", "0"]], [["-15/4", "-7", "-5/2"], ["-23/8", "-21/4", "-15/8"], ["1", "0", "0"]]], "MW_orders": [2, 0, 0, 0], "gens_reduced": true}]}, {"coeffs": ["1"], "found_pts": 2, "base_pt": [0, 0, 0, 0, 1], "loc_solv": true, "loc_solv_error": false, "pts": null, "verified": false, "g1": [{"g": [-2, 0, 1], "aInv": [["0", "0"], ["8", "-6"], ["0", "0"], ["-4", "-6"], ["-8", "-4"]], "rank": 2, "MW_proven": true, "chabauty_possible": true, "chabauty_memory_error": false, "gens": [[["-2", "0"], ["-4", "2"], ["1", "0"]], [["46", "32"], ["436", "306"], ["1", "0"]]], "MW_orders": [0, 0], "gens_reduced": true}, {"g": [-4, -6, 4, 5], "aInv": [["0", "0", "0"], ["22", "-7", "-15"], ["0", "0", "0"], ["160", "-6", "-145"], ["180", "-58", "-110"]], "rank": 2, "MW_proven": true, "chabauty_possible": true, "chabauty_memory_error": false, "gens": [[["-6", "-1", "5"], ["0", "0", "0"], ["1", "0", "0"]], [["-5", "7/4", "55/8"], ["-9/4", "-5/2", "25/16"], ["1", "0", "0"]], [["-503/64", "-149/64", "1015/128"], ["-4653/512", "-3367/512", "14645/1024"], ["1", "0", "0"]]], "MW_orders": [2, 0, 0], "gens_reduced": true}]}, {"coeffs": ["-8", "-11", "13", "16", "-4", "-5"], "found_pts": 2, "base_pt": [1, 0, 0, 0, 0], "loc_solv": true, "loc_solv_error": false, "pts": null, "verified": false, "g1": [{"g": [-2, 0, 1], "aInv": [["0", "0"], ["-2", "2"], ["0", "0"], ["-18", "-13"], ["34", "24"]], "rank": 1, "MW_proven": true, "chabauty_possible": true, "chabauty_memory_error": false, "gens": [[["0", "0"], ["4", "3"], ["1", "0"]]], "MW_orders": [0], "gens_reduced": true}, {"g": [-4, -6, 4, 5], "aInv": [["0", "0", "0"], ["28", "3", "-55/2"], ["0", "0", "0"], ["242", "100", "-625/2"], ["662", "378", "-1905/2"]], "rank": 1, "MW_proven": true, "chabauty_possible": true, "chabauty_memory_error": false, "gens": [[["0", "3", "-5/2"], ["0", "0", "0"], ["1", "0", "0"]], [["-17", "-37/4", "195/8"], ["-71/4", "-45/4", "425/16"], ["1", "0", "0"]]], "MW_orders": [2, 0], "gens_reduced": true}]}, {"coeffs": ["-4", "10", "36", "5", "-31", "-15"], "found_pts": 0, "base_pt": null, "loc_solv": false, "loc_solv_error": false, "pts": [], "verified": true, "g1": [{"g": [-2, 0, 1], "aInv": null, "rank": null, "MW_proven": null, "chabauty_possible": null, "chabauty_memory_error": false, "gens": null}, {"g": [-4, -6, 4, 5], "aInv": null, "rank": null, "MW_proven": null, "chabauty_possible": null, "chabauty_memory_error": false, "gens": null}]}], "stage": "reduce", "runtime": 68.11355352401733, "exception": false}