{"label": "36794.a.73588.1", "conductor": 36794, "disc": 73588, "coeffs": [0, -4, -7, 2, 1, -4, 4], "pts": [[-1, 2, 1], [-1, -2, 1], [0, 0, 1], [4, 112, 1], [4, -112, 1], [-1, 4, 2], [-1, -4, 2], [1, 2, 0], [1, -2, 0]], "count": 9, "root": 0, "g": [[-4, -7, 2, 1, -4, 4]], "x-coords": [[-1, 1], [0, 1], [4, 1], [-1, 2], [1, 0]], "verified": true, "hasse_principle": true, "obstruction_found": false, "search_bound": 10000, "twists": [{"coeffs": ["-1", "-1"], "found_pts": 0, "base_pt": null, "loc_solv": false, "pts": [], "verified": true, "g1": [{"g": [-4, -7, 2, 1, -4, 4], "aInv": null, "rank": null, "MW_proven": null, "gens": null, "gens_reduced": null}]}, {"coeffs": ["4", "8", "-1", "-1", "4", "-4"], "found_pts": 1, "base_pt": [1, 0, 0, 0, 0], "loc_solv": true, "pts": [[1, 0, 0, 0, 0]], "verified": true, "g1": [{"g": [-4, -7, 2, 1, -4, 4], "aInv": [["0", "0", "0", "0", "0"], ["13", "-5", "-20", "12", "0"], ["0", "0", "0", "0", "0"], ["-2376", "-3682", "3943", "4228", "-3060"], ["-95628", "-94473", "276055", "174280", "-202372"]], "rank": 1, "MW_proven": true, "gens": [[["-93/4", "-235/16", "433/16", "9/2", "-23/4"], ["289/16", "-805/64", "-2747/64", "147/4", "-75/16"], ["1", "0", "0", "0", "0"]]], "gens_reduced": true, "MW_orders": [0]}]}, {"coeffs": ["1"], "found_pts": 2, "base_pt": [0, 0, 0, 0, 1], "loc_solv": true, "pts": [[0, 0, 0, 0, 1], [20, -12, 8, -6, 5]], "verified": true, "g1": [{"g": [-4, -7, 2, 1, -4, 4], "aInv": [["0", "0", "0", "0", "0"], ["89", "31", "-92", "108", "-64"], ["0", "0", "0", "0", "0"], ["-1760", "-1412", "529", "-1660", "180"], ["16668", "36741", "17665", "10312", "20644"]], "rank": 2, "MW_proven": true, "gens": [[["-128", "-20", "119", "-140", "92"], ["-64", "56", "0", "-16", "32"], ["1", "0", "0", "0", "0"]], [["14808/4489", "-11652/4489", "40359/4489", "-18252/4489", "17436/4489"], ["-30937944/300763", "-21360280/300763", "16379560/300763", "-32072496/300763", "8862912/300763"], ["1", "0", "0", "0", "0"]]], "gens_reduced": true, "MW_orders": [0, 0]}]}, {"coeffs": ["-4", "-8", "2", "1", "-4", "4"], "found_pts": 2, "base_pt": [1, 0, 0, 0, 0], "loc_solv": true, "pts": [[3, -2, 2, 0, 1], [1, 0, 0, 0, 0]], "verified": true, "g1": [{"g": [-4, -7, 2, 1, -4, 4], "aInv": [["0", "0", "0", "0", "0"], ["257", "23", "-176", "240", "-152"], ["0", "0", "0", "0", "0"], ["13688", "2414", "-10889", "14020", "-8628"], ["209332", "48807", "-181513", "226552", "-137188"]], "rank": 3, "MW_proven": true, "gens": [[["-112", "-14", "81", "-108", "68"], ["-236", "-95", "255", "-296", "172"], ["1", "0", "0", "0", "0"]], [["-224", "-37", "174", "-226", "140"], ["200", "153", "-308", "325", "-178"], ["1", "0", "0", "0", "0"]], [["-112", "33", "26", "-64", "48"], ["3548", "904", "-3168", "3916", "-2360"], ["1", "0", "0", "0", "0"]]], "gens_reduced": true, "MW_orders": [0, 0, 0]}]}], "runtime": 408.0113787651062, "exception": false, "timeout": false}