{"label": "776261.a.776261.1", "conductor": 776261, "disc": 776261, "coeffs": [0, 4, 12, -8, -12, 0, 1], "pts": null, "count": null, "root": 0, "g": [[4, 12, -8, -12, 0, 1]], "x-coords": null, "verified": false, "hasse_principle": true, "obstruction_found": false, "search_bound": 100000, "twists": [{"coeffs": ["4", "11", "-8", "-12", "0", "1"], "found_pts": 2, "base_pt": [1, 0, 0, 0, 0], "loc_solv": true, "pts": null, "verified": false, "g1": [{"g": [4, 12, -8, -12, 0, 1], "aInv": [["0", "0", "0", "0", "0"], ["-131", "36", "108", "3", "-9"], ["0", "0", "0", "0", "0"], ["-6279", "2088", "5610", "141", "-471"], ["879534", "-291899", "-785813", "-19810", "65979"]], "rank": 2, "MW_proven": true, "gens": [[["-65", "17", "59", "2", "-5"], ["679", "-234", "-608", "-29/2", "51"], ["1", "0", "0", "0", "0"]], [["1667/25", "-671/25", "-1273/25", "-8/25", "103/25"], ["-44777/125", "18926/125", "37638/125", "771/250", "-3093/125"], ["1", "0", "0", "0", "0"]]], "gens_reduced": true, "MW_orders": [0, 0]}]}, {"coeffs": ["1"], "found_pts": 1, "base_pt": [0, 0, 0, 0, 1], "loc_solv": true, "pts": null, "verified": false, "g1": [{"g": [4, 12, -8, -12, 0, 1], "aInv": [["0", "0", "0", "0", "0"], ["1", "3", "-2", "0", "0"], ["0", "0", "0", "0", "0"], ["-3", "-6", "15", "3", "-9"], ["154", "423", "-410", "-342", "78"]], "rank": 1, "MW_proven": false, "gens": [[["-3/4", "-3/2", "17/4", "0", "0"], ["-5/8", "-9/8", "17/8", "-27/8", "0"], ["1", "0", "0", "0", "0"]]], "gens_reduced": true, "MW_orders": [0]}]}, {"coeffs": ["-2", "-11/2", "5", "6", "0", "-1/2"], "found_pts": 2, "base_pt": [1, 0, 0, 0, 0], "loc_solv": true, "pts": null, "verified": false, "g1": [{"g": [4, 12, -8, -12, 0, 1], "aInv": [["0", "0", "0", "0", "0"], ["-19", "17", "9", "-7", "1"], ["0", "0", "0", "0", "0"], ["-963", "-1974", "2445", "1503", "-552"], ["-115382", "-318685", "349714", "233139", "-83322"]], "rank": 3, "MW_proven": true, "gens": [[["19", "-17", "-9", "7", "-1"], ["-13", "-82", "71", "56", "-19"], ["1", "0", "0", "0", "0"]], [["966/25", "468/25", "-278/5", "-527/25", "47/5"], ["27398/125", "94671/125", "-96169/125", "-135237/250", "23756/125"], ["1", "0", "0", "0", "0"]], [["1008759887/311981569", "-3385947450/311981569", "1261006289/311981569", "2026810994/311981569", "-2339046299/1247926276"], ["-437061597169278/5510530453247", "-625276292674407/11021060906494", "706602839604614/5510530453247", "612079658757705/11021060906494", "-128587923043262/5510530453247"], ["1", "0", "0", "0", "0"]]], "gens_reduced": true, "MW_orders": [0, 0, 0]}]}, {"coeffs": ["-1/2", "-1"], "found_pts": 0, "base_pt": null, "loc_solv": false, "pts": [], "verified": true, "g1": [{"g": [4, 12, -8, -12, 0, 1], "aInv": null, "rank": null, "MW_proven": null, "gens": null, "gens_reduced": null}]}], "runtime": 268.74010133743286, "exception": false}