{"label": "437600.a.875200.1", "conductor": 437600, "disc": 875200, "coeffs": [0, 8, 4, 32, 36, 12, 1], "pts": null, "count": null, "root": 0, "g": [[2, 1], [4, 0, 16, 10, 1]], "x-coords": null, "verified": false, "hasse_principle": false, "obstruction_found": true, "search_bound": 100000, "twists": [{"coeffs": ["-16", "2", "-63", "-40", "-4"], "found_pts": 1, "base_pt": [0, -1, 2, -4, 8], "loc_solv": true, "pts": null, "verified": false, "g1": [{"g": [2, 1], "aInv": null, "rank": null, "MW_proven": null, "gens": null, "gens_reduced": null}, {"g": [4, 0, 16, 10, 1], "aInv": null, "rank": null, "MW_proven": null, "gens": null, "gens_reduced": null}]}, {"coeffs": ["1"], "found_pts": 2, "base_pt": [0, 0, 0, 0, 1], "loc_solv": true, "pts": null, "verified": false, "g1": [{"g": [2, 1], "aInv": null, "rank": null, "MW_proven": null, "gens": null, "gens_reduced": null}, {"g": [4, 0, 16, 10, 1], "aInv": null, "rank": null, "MW_proven": null, "gens": null, "gens_reduced": null}]}, {"coeffs": ["2/3", "-1"], "found_pts": 1, "base_pt": [-3, -2, 10, -16, 12], "loc_solv": true, "pts": null, "verified": false, "g1": [{"g": [2, 1], "aInv": null, "rank": null, "MW_proven": null, "gens": null, "gens_reduced": null}, {"g": [4, 0, 16, 10, 1], "aInv": null, "rank": null, "MW_proven": null, "gens": null, "gens_reduced": null}]}, {"coeffs": ["-32/3", "52/3", "-44", "109/3", "112/3", "4"], "found_pts": 0, "base_pt": null, "loc_solv": true, "pts": null, "verified": false, "g1": [{"g": [2, 1], "aInv": null, "rank": null, "MW_proven": null, "gens": null, "gens_reduced": null}, {"g": [4, 0, 16, 10, 1], "aInv": null, "rank": null, "MW_proven": null, "gens": null, "gens_reduced": null}]}, {"coeffs": ["8", "3", "32", "36", "12", "1"], "found_pts": 3, "base_pt": [1, 0, 0, 0, 0], "loc_solv": true, "pts": null, "verified": false, "g1": [{"g": [2, 1], "aInv": null, "rank": null, "MW_proven": null, "gens": null, "gens_reduced": null}, {"g": [4, 0, 16, 10, 1], "aInv": null, "rank": null, "MW_proven": null, "gens": null, "gens_reduced": null}]}, {"coeffs": ["-128", "-48", "-514", "-513", "-152", "-12"], "found_pts": 0, "base_pt": null, "loc_solv": true, "pts": null, "verified": false, "g1": [{"g": [2, 1], "aInv": null, "rank": null, "MW_proven": null, "gens": null, "gens_reduced": null}, {"g": [4, 0, 16, 10, 1], "aInv": null, "rank": null, "MW_proven": null, "gens": null, "gens_reduced": null}]}, {"coeffs": ["16/3", "2", "67/3", "24", "8", "2/3"], "found_pts": 2, "base_pt": [1, 0, 0, 0, 0], "loc_solv": true, "pts": null, "verified": false, "g1": [{"g": [2, 1], "aInv": null, "rank": null, "MW_proven": null, "gens": null, "gens_reduced": null}, {"g": [4, 0, 16, 10, 1], "aInv": null, "rank": null, "MW_proven": null, "gens": null, "gens_reduced": null}]}, {"coeffs": ["-256/3", "0", "-1028/3", "-212", "-61/3"], "found_pts": 3, "base_pt": [29, -26, 28, -72, 156], "loc_solv": true, "pts": null, "verified": false, "g1": [{"g": [2, 1], "aInv": null, "rank": null, "MW_proven": null, "gens": null, "gens_reduced": null}, {"g": [4, 0, 16, 10, 1], "aInv": null, "rank": null, "MW_proven": null, "gens": null, "gens_reduced": null}]}], "runtime": 25.814029216766357, "exception": false, "timeout": false}