{"label": "383320.a.766640.1", "conductor": 383320, "disc": 766640, "coeffs": [1, 6, 1, -16, -16, 0, 4], "pts": null, "count": null, "root": -1, "g": [[1, 5, -4, -12, -4, 4]], "x-coords": null, "verified": false, "hasse_principle": true, "obstruction_found": true, "search_bound": 100000, "twists": [{"coeffs": ["1", "6", "-3", "-12", "-4", "4"], "found_pts": 1, "base_pt": [1, -1, 1, -1, 1], "loc_solv": true, "pts": null, "verified": false, "g1": [{"g": [1, 5, -4, -12, -4, 4], "aInv": [["0", "0", "0", "0", "0"], ["4", "20", "-16", "-36", "-24"], ["0", "0", "0", "0", "0"], ["-1146", "-6208", "1982", "14520", "10708"], ["156596", "849506", "-265418", "-1991568", "-1472880"]], "rank": 1, "MW_proven": true, "gens": [[["-7/4", "-15/2", "57/4", "12", "8"], ["5/8", "15/8", "-41/8", "109/8", "0"], ["1", "0", "0", "0", "0"]]], "gens_reduced": false, "MW_orders": [0]}]}, {"coeffs": ["1"], "found_pts": 3, "base_pt": [0, 0, 0, 0, 1], "loc_solv": true, "pts": null, "verified": false, "g1": [{"g": [1, 5, -4, -12, -4, 4], "aInv": [["0", "0", "0", "0", "0"], ["-76", "24", "156", "68", "-56"], ["0", "0", "0", "0", "0"], ["-2114", "748", "4370", "1872", "-1572"], ["225050", "-80552", "-466258", "-199216", "167824"]], "rank": 6, "MW_proven": true, "gens": [[["1474/35", "-50/7", "-540/7", "-1256/35", "988/35"], ["342606/1225", "-21872/175", "-749958/1225", "-62068/245", "268076/1225"], ["1", "0", "0", "0", "0"]], [["1493717/841", "-534525/841", "-3095636/841", "-1322894/841", "1114164/841"], ["1786564792/24389", "-641670498/24389", "-3704436686/24389", "-1582100540/24389", "1333228120/24389"], ["1", "0", "0", "0", "0"]], [["134/7", "-78/7", "-328/7", "-132/7", "116/7"], ["19589/49", "-1103/7", "-41592/49", "-17546/49", "14932/49"], ["1", "0", "0", "0", "0"]], [["-5079/121", "2759/121", "11432/121", "4534/121", "-4020/121"], ["-405216/1331", "174136/1331", "876856/1331", "367724/1331", "-313628/1331"], ["1", "0", "0", "0", "0"]], [["11379209/94249", "2879/94249", "-18239712/94249", "-9077082/94249", "6768468/94249"], ["19250315208/28934443", "-14934362006/28934443", "-50805958550/28934443", "-19147133512/28934443", "17843673568/28934443"], ["1", "0", "0", "0", "0"]], [["194612/1849", "-121362/1849", "-378052/1849", "-30754/1849", "92452/1849"], ["103320363/159014", "-44012161/159014", "-125503715/79507", "-6295303/79507", "29595308/79507"], ["1", "0", "0", "0", "0"]]], "gens_reduced": false, "MW_orders": [0, 0, 0, 0, 0, 0]}]}, {"coeffs": ["-4", "-21", "14", "47", "16", "-16"], "found_pts": 0, "base_pt": null, "loc_solv": false, "pts": [], "verified": true, "g1": [{"g": [1, 5, -4, -12, -4, 4], "aInv": null, "rank": null, "MW_proven": null, "gens": null, "gens_reduced": null}]}, {"coeffs": ["0", "4", "-4", "-12", "-4", "4"], "found_pts": 1, "base_pt": [1, -1, 1, -1, 1], "loc_solv": true, "pts": null, "verified": false, "g1": [{"g": [1, 5, -4, -12, -4, 4], "aInv": [["0", "0", "0", "0", "0"], ["-18", "-14", "16", "16", "-8"], ["0", "0", "0", "0", "0"], ["-182", "-640", "-590", "-24", "172"], ["27762", "174198", "192764", "23764", "-59244"]], "rank": null, "MW_proven": null, "gens": null, "gens_reduced": null}]}], "runtime": 841.0539555549622, "exception": false, "timeout": false}