{"label": "110636.a.442544.1", "conductor": 110636, "disc": 442544, "coeffs": [0, 4, -23, 36, 4, -16, 4], "pts": null, "count": null, "root": 0, "g": [[4, -23, 36, 4, -16, 4]], "x-coords": [[1, 0]], "verified": false, "hasse_principle": true, "obstruction_found": false, "search_bound": 100000, "twists": [{"coeffs": ["4", "-24", "36", "4", "-16", "4"], "found_pts": 1, "base_pt": [1, 0, 0, 0, 0], "loc_solv": true, "pts": [[1, 0, 0, 0, 0]], "verified": true, "g1": [{"g": [4, -23, 36, 4, -16, 4], "aInv": [["0", "0", "0", "0", "0"], ["-300", "1068", "-40", "-436", "120"], ["0", "0", "0", "0", "0"], ["181232", "-551896", "9466", "226636", "-61420"], ["14106288", "-27124420", "-1695076", "11435008", "-2925076"]], "rank": 2, "MW_proven": true, "gens": [[["457", "-7435/4", "97", "755", "-210"], ["7573/4", "-57635/16", "-935/4", "12157/8", "-388"], ["1", "0", "0", "0", "0"]], [["3772/9", "-16072/9", "947/9", "2176/3", "-1828/9"], ["-84938/27", "410911/54", "4202/27", "-28412/9", "22424/27"], ["1", "0", "0", "0", "0"]]], "gens_reduced": true, "MW_orders": [0, 0], "Ecov": [[[[1, -7, "31/2", -10, 2], ["-17/8", 14, "-61/2", 21, "-9/2"], [-9, -5, 7, "-3/2", 0]], [[1, 0, 1], [0, 1, 1], [0, 0, 2]]], [[["1/2", -4, 10, -8, 2], [-6, -8, "7/2", 0, 0]], [[1, 0, 1], [0, 0, 2]]]]}]}, {"coeffs": ["1"], "found_pts": 4, "base_pt": [0, 0, 0, 0, 1], "loc_solv": true, "pts": null, "verified": false, "g1": [{"g": [4, -23, 36, 4, -16, 4], "aInv": [["0", "0", "0", "0", "0"], ["20", "-92", "80", "36", "-24"], ["0", "0", "0", "0", "0"], ["2192", "-11312", "13882", "7100", "-4876"], ["-224368", "1198292", "-1534716", "-839304", "566452"]], "rank": null, "MW_proven": null, "gens": null, "gens_reduced": null, "Ecov": [[[[-12, 9, 67, "-115/2", 12], ["4527/32", "-141497/128", "64135/32", "-36297/32", "3201/16"]], [[1, 0, 1], [0, 0, 2]]], [[["-9/4", "-493/16", "1723/16", "-2357/32", "57/4"], ["7/2", "-161/8", "47/2", -7, "1/4"], ["1639/8", "-45749/32", "96871/32", "-3671/2", "10749/32"]], [[1, 0, 1], [0, 1, 1], [0, 0, 2]]]]}]}, {"coeffs": ["1/2", "-5/2", "1"], "found_pts": 1, "base_pt": [2, 2, 4, 9, 20], "loc_solv": true, "pts": null, "verified": false, "g1": [{"g": [4, -23, 36, 4, -16, 4], "aInv": [["0", "0", "0", "0", "0"], ["132", "-772", "68", "308", "-88"], ["0", "0", "0", "0", "0"], ["40400", "-366512", "39534", "145940", "-42228"], ["-21214960", "97403652", "-6146424", "-39385020", "11033964"]], "rank": null, "MW_proven": null, "gens": null, "gens_reduced": null, "Ecov": [[[["-4156/81", "21848/81", "-976/3", "-37643/162", "1148/9"], ["3179/3", "-50653/9", "63577/9", "112840/27", "-65896/27"], ["1699/162", "-15751/216", "4312/27", "-8080/81", "1523/81"]], [[1, 0, 1], [0, 1, 1], [0, 0, 2]]], [[["8570/81", "-45400/81", "2090/3", "70105/162", "-2236/9"], ["3179/3", "-50653/9", "63577/9", "112840/27", "-65896/27"], [-6, "6365/162", "-6913/81", "4799/81", "-2083/162"]], [[1, 0, 1], [0, 1, 1], [0, 0, 2]]]]}]}, {"coeffs": ["2", "-12", "41/2", "1", "-8", "2"], "found_pts": 0, "base_pt": null, "loc_solv": false, "pts": [], "verified": true, "g1": [{"g": [4, -23, 36, 4, -16, 4], "aInv": null, "rank": null, "MW_proven": null, "gens": null, "gens_reduced": null}]}], "runtime": 381.35284328460693, "exception": false, "timeout": true}