{"label": "57649.a.57649.1", "conductor": 57649, "disc": 57649, "coeffs": [0, -4, 12, 8, 9, 2, 1], "pts": null, "count": null, "root": 0, "g": [[-4, 12, 8, 9, 2, 1]], "x-coords": null, "verified": false, "hasse_principle": true, "obstruction_found": true, "search_bound": 10000, "twists": [{"coeffs": ["-4", "11", "8", "9", "2", "1"], "found_pts": 1, "base_pt": [1, 0, 0, 0, 0], "loc_solv": true, "pts": null, "verified": false, "g1": [{"g": [-4, 12, 8, 9, 2, 1], "aInv": [["0", "0", "0", "0", "0"], ["9", "5", "4", "0", "0"], ["0", "0", "0", "0", "0"], ["-32", "12", "2", "8", "2"], ["-320", "-204", "-236", "-56", "-28"]], "rank": 3, "MW_proven": true, "gens": [[["-8", "0", "-2", "0", "0"], ["0", "-4", "-11", "-3", "-2"], ["1", "0", "0", "0", "0"]], [["839123/36481", "1157910/36481", "847297/36481", "1126669/145924", "424053/145924"], ["1182757702/6967871", "977502524/6967871", "994831588/6967871", "450444487/13935742", "223291385/13935742"], ["1", "0", "0", "0", "0"]], [["9368/289", "7492/289", "7318/289", "1856/289", "852/289"], ["-1180600/4913", "-799488/4913", "-735785/4913", "-170377/4913", "-74666/4913"], ["1", "0", "0", "0", "0"]]], "gens_reduced": false, "MW_orders": [0, 0, 0]}]}, {"coeffs": ["-16", "44", "31", "35", "8", "4"], "found_pts": 2, "base_pt": [-1, 1, -1, -3, 3], "loc_solv": true, "pts": null, "verified": false, "g1": [{"g": [-4, 12, 8, 9, 2, 1], "aInv": [["0", "0", "0", "0", "0"], ["1", "1", "-5", "-3", "-2"], ["0", "0", "0", "0", "0"], ["-16", "28", "98", "52", "30"], ["80", "-172", "-396", "-232", "-116"]], "rank": 2, "MW_proven": true, "gens": [[["-1", "2", "-3", "33/16", "1/16"], ["67/8", "-129/4", "49/8", "-19/2", "15/8"], ["1", "0", "0", "0", "0"]], [["0", "-2", "-1", "0", "0"], ["0", "0", "0", "1", "0"], ["1", "0", "0", "0", "0"]]], "gens_reduced": false, "MW_orders": [0, 0]}]}, {"coeffs": ["1"], "found_pts": 2, "base_pt": [0, 0, 0, 0, 1], "loc_solv": true, "pts": null, "verified": false, "g1": [{"g": [-4, 12, 8, 9, 2, 1], "aInv": [["0", "0", "0", "0", "0"], ["25", "11", "11", "2", "1"], ["0", "0", "0", "0", "0"], ["64", "-868", "-478", "-200", "-62"], ["-4512", "-8828", "-11828", "-2780", "-1680"]], "rank": 2, "MW_proven": false, "gens": [[["-16", "-26", "-6", "-4", "0"], ["0", "-10", "-25", "-5", "-4"], ["1", "0", "0", "0", "0"]], [["59", "46", "64", "53/4", "33/4"], ["-558", "-638", "-477", "-275/2", "-103/2"], ["1", "0", "0", "0", "0"]]], "gens_reduced": false, "MW_orders": [0, 0]}]}, {"coeffs": ["4", "1", "1"], "found_pts": 0, "base_pt": null, "loc_solv": false, "pts": [], "verified": true, "g1": [{"g": [-4, 12, 8, 9, 2, 1], "aInv": null, "rank": null, "MW_proven": null, "gens": null, "gens_reduced": null}]}], "runtime": 636.1060357093811, "exception": false, "timeout": false}