{"label": "623729.a.623729.1", "conductor": 623729, "disc": 623729, "coeffs": [0, 4, 17, 2, -49, -14, 41], "pts": null, "count": null, "root": 0, "g": [[4, 17, 2, -49, -14, 41]], "x-coords": [], "verified": false, "hasse_principle": true, "obstruction_found": false, "search_bound": 100000, "twists": [{"coeffs": ["-1/2", "-1/2", "1"], "found_pts": 0, "base_pt": null, "loc_solv": false, "pts": [], "verified": true, "g1": [{"g": [4, 17, 2, -49, -14, 41], "aInv": null, "rank": null, "MW_proven": null, "gens": null, "gens_reduced": null}]}, {"coeffs": ["1"], "found_pts": 1, "base_pt": [0, 0, 0, 0, 1], "loc_solv": true, "pts": null, "verified": false, "g1": [{"g": [4, 17, 2, -49, -14, 41], "aInv": [["0", "0", "0", "0", "0"], ["231", "342", "-1630", "-962", "2337"], ["0", "0", "0", "0", "0"], ["48912", "103892", "-226315", "-218658", "304876"], ["-4492548", "-10372708", "17930338", "20373306", "-23810873"]], "rank": 1, "MW_proven": false, "gens": [[["-839/2", "-8219/8", "1557", "31415/16", "-16523/8"], ["26681/32", "341093/128", "-106207/128", "-522377/128", "23411/32"], ["1", "0", "0", "0", "0"]]], "gens_reduced": true, "MW_orders": [0]}]}, {"coeffs": ["-2", "-8", "-1", "23", "8", "-41/2"], "found_pts": 1, "base_pt": [3, 4, 4, 4, 4], "loc_solv": true, "pts": null, "verified": false, "g1": [{"g": [4, 17, 2, -49, -14, 41], "aInv": [["0", "0", "0", "0", "0"], ["-49", "-112", "13", "82", "0"], ["0", "0", "0", "0", "0"], ["-624", "460", "6179", "1932", "-7339"], ["6828", "496", "-36376", "-2006", "39975"]], "rank": 1, "MW_proven": false, "gens": [[["314", "595", "-3771/4", "-1131", "1271"], ["-2320", "-4420", "29581/4", "70645/8", "-40467/4"], ["1", "0", "0", "0", "0"]]], "gens_reduced": true, "MW_orders": [0]}]}, {"coeffs": ["4", "16", "3", "-49", "-14", "41"], "found_pts": 1, "base_pt": [1, 0, 0, 0, 0], "loc_solv": true, "pts": null, "verified": false, "g1": [{"g": [4, 17, 2, -49, -14, 41], "aInv": [["0", "0", "0", "0", "0"], ["-49", "35", "55", "-41", "0"], ["0", "0", "0", "0", "0"], ["-3744", "2620", "4154", "756", "-3895"], ["208716", "-154808", "-271753", "77329", "145878"]], "rank": 0, "MW_proven": false, "gens": [], "gens_reduced": true, "MW_orders": []}]}], "runtime": 1018.1582109928131, "exception": false}