{"label": "419929.a.419929.1", "conductor": 419929, "disc": 419929, "coeffs": [0, -4, 60, -88, -15, 6, 1], "pts": null, "count": null, "root": 0, "g": [[-4, 60, -88, -15, 6, 1]], "x-coords": [], "verified": false, "hasse_principle": true, "obstruction_found": false, "search_bound": 100000, "twists": [{"coeffs": ["-4", "59", "-88", "-15", "6", "1"], "found_pts": 2, "base_pt": [1, 0, 0, 0, 0], "loc_solv": true, "pts": null, "verified": false, "g1": [{"g": [-4, 60, -88, -15, 6, 1], "aInv": [["0", "0", "0", "0", "0"], ["-15", "6", "1", "0", "0"], ["0", "0", "0", "0", "0"], ["-768", "174", "81", "-12", "-3"], ["13480", "-6176", "-1803", "398", "81"]], "rank": null, "MW_proven": null, "gens": null, "gens_reduced": null, "Ecov": [[[[-3, "-1/2", 0, 0, 0], [1, 0, 0, 0, 0], [88, 15, -6, -1, 0]], [[1, 0, 1], [0, 1, 1], [0, 0, 2]]], [[[2, 0, 0, 0, 0], [-48, 6, "3/2", 0, 0]], [[1, 0, 1], [0, 0, 2]]]]}]}, {"coeffs": ["-1/2", "9/2", "1"], "found_pts": 1, "base_pt": [-13, -3, 7, -33, 127], "loc_solv": true, "pts": null, "verified": false, "g1": [{"g": [-4, 60, -88, -15, 6, 1], "aInv": [["0", "0", "0", "0", "0"], ["273", "-261", "-317", "-289/2", "-37/2"], ["0", "0", "0", "0", "0"], ["85284", "-966078", "1125305", "551855", "57536"], ["-57194356", "849180576", "-1035470833", "-502489293", "-52232854"]], "rank": null, "MW_proven": null, "gens": null, "gens_reduced": null, "Ecov": [[[["-13495951/729", "-425542807/13122", "-28380863/13122", "30269699/13122", "232096/729"], ["920675/81", "-115111136/729", "-27563333/1458", "2668456/243", "2439193/1458"], ["17199003613/6561", "-28934001794/6561", "-487762397/729", "8399049329/26244", "1347892751/26244"]], [[1, 0, 1], [0, 1, 1], [0, 0, 2]]], [[["-26996924/729", "759832739/6561", "106506817/6561", "-52375897/6561", "-919774/729"], ["1841350/81", "-230222272/729", "-27563333/729", "5336912/243", "2439193/729"], ["-17905558048/6561", "9964535888/2187", "9841348567/13122", "-674355013/2187", "-334064533/6561"]], [[1, 0, 1], [0, 1, 1], [0, 0, 2]]]]}]}, {"coeffs": ["2", "-59/2", "79/2", "13/2", "-3", "-1/2"], "found_pts": 0, "base_pt": null, "loc_solv": false, "pts": [], "verified": true, "g1": [{"g": [-4, 60, -88, -15, 6, 1], "aInv": null, "rank": null, "MW_proven": null, "gens": null, "gens_reduced": null}]}, {"coeffs": ["1"], "found_pts": 1, "base_pt": [0, 0, 0, 0, 1], "loc_solv": true, "pts": null, "verified": false, "g1": [{"g": [-4, 60, -88, -15, 6, 1], "aInv": [["0", "0", "0", "0", "0"], ["137", "-1970", "2797", "-219/2", "-285/2"], ["0", "0", "0", "0", "0"], ["6516", "-81954", "-64767", "10215", "3812"], ["-961472", "12109756", "9522623", "-1500137", "-562210"]], "rank": null, "MW_proven": null, "gens": null, "gens_reduced": null, "Ecov": [[[[-35220, 97158, -43843, -29233, -3262], [-14195, "140937/2", "70713/4", -1567, "-1739/4"]], [[1, 0, 1], [0, 0, 2]]], [[["-48579/2", "726373/4", "-760487/4", "-382403/4", "-40125/4"], [-33195, "633311/2", -355225, "-702707/4", "-73415/4"], [-21609, "85665/2", "-4559/2", -6418, -816]], [[1, 0, 1], [0, 1, 1], [0, 0, 2]]]]}]}], "runtime": 113.52876615524292, "exception": false, "timeout": true}