{"label": "310079.a.310079.1", "conductor": 310079, "disc": 310079, "coeffs": [0, 4, 8, 4, -3, 0, 4], "pts": null, "count": null, "root": 0, "g": [[4, 8, 4, -3, 0, 4]], "x-coords": null, "verified": false, "hasse_principle": true, "obstruction_found": false, "search_bound": 100000, "twists": [{"coeffs": ["-16", "-32", "-17", "11", "0", "-16"], "found_pts": 0, "base_pt": null, "loc_solv": false, "pts": [], "verified": true, "g1": [{"g": [4, 8, 4, -3, 0, 4], "aInv": null, "rank": null, "MW_proven": null, "gens": null, "gens_reduced": null}]}, {"coeffs": ["4", "7", "4", "-3", "0", "4"], "found_pts": 1, "base_pt": [1, 0, 0, 0, 0], "loc_solv": true, "pts": null, "verified": false, "g1": [{"g": [4, 8, 4, -3, 0, 4], "aInv": [["0", "0", "0", "0", "0"], ["-3", "0", "4", "0", "0"], ["0", "0", "0", "0", "0"], ["-128", "-48", "36", "0", "-48"], ["448", "224", "-236", "64", "144"]], "rank": 2, "MW_proven": true, "gens": [[["3", "0", "-3", "0", "0"], ["8", "-3", "0", "5", "0"], ["1", "0", "0", "0", "0"]], [["9148/2401", "-13752/2401", "5325/2401", "3600/2401", "-4028/2401"], ["-3293236/117649", "-4734794/117649", "2430193/117649", "1328072/117649", "-2961132/117649"], ["1", "0", "0", "0", "0"]]], "gens_reduced": true, "MW_orders": [0, 0]}]}, {"coeffs": ["-4", "-7", "-3", "3", "0", "-4"], "found_pts": 2, "base_pt": [1, 0, 0, 0, 0], "loc_solv": true, "pts": null, "verified": false, "g1": [{"g": [4, 8, 4, -3, 0, 4], "aInv": [["0", "0", "0", "0", "0"], ["-3", "-3", "4", "4", "0"], ["0", "0", "0", "0", "0"], ["-32", "-64", "4", "0", "-48"], ["-48", "80", "148", "64", "80"]], "rank": 4, "MW_proven": true, "gens": [[["8", "8", "-3", "0", "4"], ["0", "0", "-3", "0", "4"], ["1", "0", "0", "0", "0"]], [["1880/289", "1900/289", "-1371/289", "-112/289", "1316/289"], ["17752/4913", "13612/4913", "44505/4913", "32432/4913", "-27340/4913"], ["1", "0", "0", "0", "0"]], [["11865088/683929", "18988048/683929", "-18434149/683929", "-19358848/683929", "9506396/683929"], ["-1573394144/565609283", "102746760764/565609283", "117743769393/565609283", "11043187120/565609283", "14943451796/565609283"], ["1", "0", "0", "0", "0"]], [["1138865248/313750369", "806928620/313750369", "-1203388467/313750369", "-788349840/313750369", "-399921276/313750369"], ["-11942599613680/5557460286097", "5970187600564/5557460286097", "23329508999885/5557460286097", "41734661275344/5557460286097", "37995299335044/5557460286097"], ["1", "0", "0", "0", "0"]]], "gens_reduced": true, "MW_orders": [0, 0, 0, 0]}]}, {"coeffs": ["1"], "found_pts": 1, "base_pt": [0, 0, 0, 0, 1], "loc_solv": true, "pts": null, "verified": false, "g1": [{"g": [4, 8, 4, -3, 0, 4], "aInv": [["0", "0", "0", "0", "0"], ["49", "42", "3", "-40", "44"], ["0", "0", "0", "0", "0"], ["-40199552", "-34640080", "-768828", "31024832", "-35315504"], ["40230256352", "34666520656", "769449604", "-31048554752", "35342486032"]], "rank": 2, "MW_proven": true, "gens": [[["0", "0", "0", "0", "0"], ["-175640", "-151350", "-3350", "135544", "-154296"], ["1", "0", "0", "0", "0"]], [["1821/4", "391", "13/2", "-348", "398"], ["-905157/8", "-97498", "-17309/8", "87322", "-198797/2"], ["1", "0", "0", "0", "0"]]], "gens_reduced": true, "MW_orders": [0, 0]}]}], "runtime": 694.0550489425659, "exception": false}