{"label": "300741.a.300741.1", "conductor": 300741, "disc": 300741, "coeffs": [0, 4, 9, -24, 2, 8, 1], "pts": null, "count": null, "root": 0, "g": [[-1, 1], [-4, -13, 11, 9, 1]], "x-coords": [], "verified": false, "hasse_principle": true, "obstruction_found": false, "search_bound": 100000, "twists": [{"coeffs": ["-4", "-8", "23", "-3", "-8", "-1"], "found_pts": 0, "base_pt": null, "loc_solv": false, "pts": [], "verified": true, "g1": [{"g": [-1, 1], "aInv": null, "rank": null, "MW_proven": null, "gens": null, "gens_reduced": null}, {"g": [-4, -13, 11, 9, 1], "aInv": null, "rank": null, "MW_proven": null, "gens": null, "gens_reduced": null}]}, {"coeffs": ["1"], "found_pts": 2, "base_pt": [-1, -1, -1, -1, 1], "loc_solv": true, "pts": null, "verified": false, "g1": [{"g": [-1, 1], "aInv": [["0"], ["10"], ["0"], ["-108"], ["-924"]], "rank": 1, "MW_proven": true, "gens": [[["233/16"], ["3333/64"], ["1"]]], "gens_reduced": true, "MW_orders": [0]}, {"g": [-4, -13, 11, 9, 1], "aInv": [["0", "0", "0", "0"], ["24", "171/2", "-62", "-147/2"], ["0", "0", "0", "0"], ["383312", "1193833", "-1216151", "-698416"], ["1034440756", "3219188583", "-3288945739", "-1873682071"]], "rank": null, "MW_proven": null, "gens": null, "gens_reduced": null}]}, {"coeffs": ["-1", "1", "1"], "found_pts": 2, "base_pt": [-1, -1, 0, -1, 4], "loc_solv": true, "pts": null, "verified": false, "g1": [{"g": [-1, 1], "aInv": [["0"], ["-10"], ["0"], ["-108"], ["924"]], "rank": null, "MW_proven": null, "gens": null, "gens_reduced": null}, {"g": [-4, -13, 11, 9, 1], "aInv": [["0", "0", "0", "0"], ["-4368", "5227/2", "2534", "577/2"], ["0", "0", "0", "0"], ["-26287104", "14989533", "15034313", "1720544"], ["128913554852", "-73502794377", "-73718991592", "-8436374628"]], "rank": null, "MW_proven": null, "gens": null, "gens_reduced": null}]}, {"coeffs": ["16", "32", "-108", "18", "41", "5"], "found_pts": 0, "base_pt": null, "loc_solv": false, "pts": [], "verified": true, "g1": [{"g": [-1, 1], "aInv": null, "rank": null, "MW_proven": null, "gens": null, "gens_reduced": null}, {"g": [-4, -13, 11, 9, 1], "aInv": null, "rank": null, "MW_proven": null, "gens": null, "gens_reduced": null}]}, {"coeffs": ["4", "8", "-24", "2", "8", "1"], "found_pts": 2, "base_pt": [1, 0, 0, 0, 0], "loc_solv": true, "pts": null, "verified": false, "g1": [{"g": [-1, 1], "aInv": [["0"], ["-10"], ["0"], ["-108"], ["924"]], "rank": null, "MW_proven": null, "gens": null, "gens_reduced": null}, {"g": [-4, -13, 11, 9, 1], "aInv": [["0", "0", "0", "0"], ["-4252", "-24007/2", "16720", "5051/2"], ["0", "0", "0", "0"], ["-117644432", "-332915103", "463398137", "70000464"], ["-1069359084048", "-3026119833298", "4212178636077", "636287556000"]], "rank": null, "MW_proven": null, "gens": null, "gens_reduced": null}]}, {"coeffs": ["-4", "-4", "35", "-13", "-16", "-2"], "found_pts": 0, "base_pt": null, "loc_solv": false, "pts": [], "verified": true, "g1": [{"g": [-1, 1], "aInv": null, "rank": null, "MW_proven": null, "gens": null, "gens_reduced": null}, {"g": [-4, -13, 11, 9, 1], "aInv": null, "rank": null, "MW_proven": null, "gens": null, "gens_reduced": null}]}, {"coeffs": ["4", "12", "-10", "-9", "-1"], "found_pts": 1, "base_pt": [2, 1, 1, 1, 1], "loc_solv": true, "pts": null, "verified": false, "g1": [{"g": [-1, 1], "aInv": [["0"], ["-10"], ["0"], ["-108"], ["924"]], "rank": null, "MW_proven": null, "gens": null, "gens_reduced": null}, {"g": [-4, -13, 11, 9, 1], "aInv": [["0", "0", "0", "0"], ["28", "337/2", "92", "19/2"], ["0", "0", "0", "0"], ["1408", "6717", "3425", "348"], ["-1680", "-12770", "-6633", "-678"]], "rank": null, "MW_proven": null, "gens": null, "gens_reduced": null}]}, {"coeffs": ["-16", "-40", "82", "5", "-23", "-4"], "found_pts": 2, "base_pt": [67, 71, 59, 51, 47], "loc_solv": true, "pts": null, "verified": false, "g1": [{"g": [-1, 1], "aInv": [["0"], ["-10"], ["0"], ["-108"], ["924"]], "rank": null, "MW_proven": null, "gens": null, "gens_reduced": null}, {"g": [-4, -13, 11, 9, 1], "aInv": [["0", "0", "0", "0"], ["-152", "-357/2", "274", "273/2"], ["0", "0", "0", "0"], ["872752", "2748081", "-2797711", "-1595868"], ["-3558995692", "-11078328413", "11318099958", "6447056174"]], "rank": null, "MW_proven": null, "gens": null, "gens_reduced": null}]}], "runtime": 39.60746240615845, "exception": false, "timeout": true}