{"label": "112994.a.225988.1", "conductor": 112994, "disc": 225988, "coeffs": [0, 8, -3, 14, -1, 6, 1], "pts": [[1, 1, 0], [1, -1, 0], [1, 5, 1], [1, -5, 1], [0, 0, 1]], "count": 5, "root": 0, "g": [[8, -3, 14, -1, 6, 1]], "x-coords": [[1, 0], [1, 1], [0, 1]], "verified": true, "hasse_principle": true, "obstruction_found": false, "search_bound": 100000, "twists": [{"coeffs": ["1", "0", "1"], "found_pts": 0, "base_pt": null, "loc_solv": false, "pts": [], "verified": true, "g1": [{"g": [8, -3, 14, -1, 6, 1], "aInv": null, "rank": null, "MW_proven": null, "gens": null, "gens_reduced": null}]}, {"coeffs": ["8", "-4", "14", "-1", "6", "1"], "found_pts": 2, "base_pt": [1, 0, 0, 0, 0], "loc_solv": true, "pts": [[-1, -4, 0, 4, 4], [1, 0, 0, 0, 0]], "verified": true, "g1": [{"g": [8, -3, 14, -1, 6, 1], "aInv": [["0", "0", "0", "0", "0"], ["-1", "6", "1", "0", "0"], ["0", "0", "0", "0", "0"], ["96", "-48", "39", "-12", "-3"], ["124", "566", "48", "248", "39"]], "rank": 3, "MW_proven": true, "gens": [[["2", "-14", "1", "-6", "-1"], ["4", "12", "5", "7", "1"], ["1", "0", "0", "0", "0"]], [["6", "-27/2", "6", "-2", "-1/2"], ["-32", "79/2", "-77/2", "51/2", "5"], ["1", "0", "0", "0", "0"]], [["-83/4", "0", "-73/4", "-9/2", "-1/4"], ["153/8", "81/4", "135/8", "77/4", "21/8"], ["1", "0", "0", "0", "0"]]], "gens_reduced": true, "MW_orders": [0, 0, 0]}]}, {"coeffs": ["1"], "found_pts": 1, "base_pt": [0, 0, 0, 0, 1], "loc_solv": true, "pts": [[0, 0, 0, 0, 1]], "verified": true, "g1": [{"g": [8, -3, 14, -1, 6, 1], "aInv": [["0", "0", "0", "0", "0"], ["31", "-45/2", "34", "-4", "-3/2"], ["0", "0", "0", "0", "0"], ["648", "-807", "840", "-450", "-93"], ["-17668", "5104", "-16860", "-4232", "-244"]], "rank": 2, "MW_proven": true, "gens": [[["-30", "55/2", "-30", "11", "5/2"], ["-32", "48", "-44", "44", "8"], ["1", "0", "0", "0", "0"]], [["-423/16", "107/8", "-429/16", "-21/8", "5/16"], ["605/64", "-3189/32", "2879/64", "-2977/32", "-1007/64"], ["1", "0", "0", "0", "0"]]], "gens_reduced": true, "MW_orders": [0, 0]}]}, {"coeffs": ["8", "-4", "14", "-2", "6", "1"], "found_pts": 0, "base_pt": null, "loc_solv": false, "pts": [], "verified": true, "g1": [{"g": [8, -3, 14, -1, 6, 1], "aInv": null, "rank": null, "MW_proven": null, "gens": null, "gens_reduced": null}]}], "runtime": 233.63917350769043, "exception": false}