{"label": "123424.b.987392.1", "conductor": 123424, "disc": 987392, "coeffs": [0, 1, -1, -1, -1, 2, 1], "pts": null, "count": null, "root": 0, "g": [[1, -1, -1, -1, 2, 1]], "x-coords": null, "verified": false, "hasse_principle": true, "obstruction_found": false, "search_bound": 100000, "twists": [{"coeffs": ["1", "-1"], "found_pts": 1, "base_pt": [1, 1, 1, 0, 1], "loc_solv": true, "pts": null, "verified": false, "g1": [{"g": [1, -1, -1, -1, 2, 1], "aInv": [["0", "0", "0", "0", "0"], ["5", "-3", "-2", "-3", "-1"], ["0", "0", "0", "0", "0"], ["-4", "-12", "6", "18", "6"], ["-11", "-13", "8", "24", "8"]], "rank": 3, "MW_proven": true, "gens": [[["0", "2", "1", "-2", "-1"], ["-4", "0", "4", "9", "3"], ["1", "0", "0", "0", "0"]], [["5", "7", "2", "-5", "-2"], ["-19", "-18", "-7", "19", "9"], ["1", "0", "0", "0", "0"]], [["163/63", "145/63", "-62/63", "-575/63", "-230/63"], ["-4505/1323", "-1058/1323", "7645/1323", "2491/189", "6145/1323"], ["1", "0", "0", "0", "0"]]], "gens_reduced": true, "MW_orders": [0, 0, 0]}]}, {"coeffs": ["1"], "found_pts": 3, "base_pt": [-1, -1, 1, 0, 1], "loc_solv": true, "pts": null, "verified": false, "g1": [{"g": [1, -1, -1, -1, 2, 1], "aInv": [["0", "0", "0", "0", "0"], ["-4", "-5", "2", "8", "3"], ["0", "0", "0", "0", "0"], ["-6", "-14", "-12", "-8", "-2"], ["-119", "-11", "124", "281", "100"]], "rank": 4, "MW_proven": true, "gens": [[["-2", "2", "4", "6", "2"], ["-15", "-3", "13", "33", "12"], ["1", "0", "0", "0", "0"]], [["3", "-1", "-7", "-12", "-4"], ["22", "13", "-4", "-33", "-13"], ["1", "0", "0", "0", "0"]], [["-4", "0", "3", "8", "3"], ["6", "5", "1", "-7", "-3"], ["1", "0", "0", "0", "0"]], [["4", "5", "2", "-4", "-2"], ["5", "-3", "-11", "-18", "-6"], ["1", "0", "0", "0", "0"]]], "gens_reduced": true, "MW_orders": [0, 0, 0, 0]}]}, {"coeffs": ["-1", "3", "-1", "-1"], "found_pts": 2, "base_pt": [2, 1, 1, 0, 2], "loc_solv": true, "pts": null, "verified": false, "g1": [{"g": [1, -1, -1, -1, 2, 1], "aInv": [["0", "0", "0", "0", "0"], ["-4", "1", "2", "9", "4"], ["0", "0", "0", "0", "0"], ["-2", "8", "16", "14", "4"], ["-51", "-43", "-11", "56", "24"]], "rank": 3, "MW_proven": true, "gens": [[["-7", "-3", "5", "14", "5"], ["13", "5", "-7", "-24", "-9"], ["1", "0", "0", "0", "0"]], [["9", "1", "-7", "-19", "-7"], ["-3", "1", "5", "9", "3"], ["1", "0", "0", "0", "0"]], [["-12797/38809", "-54451/38809", "-1400/38809", "15372/38809", "4346/38809"], ["103404999/7645373", "26129531/7645373", "-79082422/7645373", "-216574392/7645373", "-80109418/7645373"], ["1", "0", "0", "0", "0"]]], "gens_reduced": true, "MW_orders": [0, 0, 0]}]}, {"coeffs": ["-1", "2", "1"], "found_pts": 0, "base_pt": null, "loc_solv": false, "pts": [], "verified": true, "g1": [{"g": [1, -1, -1, -1, 2, 1], "aInv": null, "rank": null, "MW_proven": null, "gens": null, "gens_reduced": null}]}], "runtime": 241.71783828735352, "exception": false}