{"label": "193371.a.193371.1", "conductor": 193371, "disc": 193371, "coeffs": [0, 4, -4, -36, 4, 96, 65], "pts": null, "count": null, "root": 0, "g": [[4, -4, -36, 4, 96, 65]], "x-coords": [], "verified": false, "hasse_principle": true, "obstruction_found": false, "search_bound": 100000, "twists": [{"coeffs": ["-1/2", "1/2", "1"], "found_pts": 1, "base_pt": [5, 0, 1, 0, 0], "loc_solv": true, "pts": null, "verified": false, "g1": [{"g": [4, -4, -36, 4, 96, 65], "aInv": [["0", "0", "0", "0", "0"], ["-11817", "27295", "68534", "-101739", "-279045/2"], ["0", "0", "0", "0", "0"], ["-18952163", "44492622", "110567892", "-167825795", "-228671625"], ["-10217643784", "23918076426", "59895305240", "-90558433063", "-247579500415/2"]], "rank": null, "MW_proven": null, "gens": null, "gens_reduced": null}]}, {"coeffs": ["1/8", "-1/4", "-5/8", "3/4", "1"], "found_pts": 0, "base_pt": null, "loc_solv": false, "pts": [], "verified": true, "g1": [{"g": [4, -4, -36, 4, 96, 65], "aInv": null, "rank": null, "MW_proven": null, "gens": null, "gens_reduced": null}]}, {"coeffs": ["1"], "found_pts": 2, "base_pt": [0, 0, 0, 0, 1], "loc_solv": true, "pts": null, "verified": false, "g1": [{"g": [4, -4, -36, 4, 96, 65], "aInv": [["0", "0", "0", "0", "0"], ["-3117", "8865", "13702", "-28321", "-62205/2"], ["0", "0", "0", "0", "0"], ["-19288915", "52118330", "84928708", "-163838131", "-184232165"], ["36247518540", "-97925433358", "-159599929108", "307818943873", "692324730565/2"]], "rank": null, "MW_proven": null, "gens": null, "gens_reduced": null}]}, {"coeffs": ["-1/4", "1/4", "1"], "found_pts": 0, "base_pt": null, "loc_solv": false, "pts": [], "verified": true, "g1": [{"g": [4, -4, -36, 4, 96, 65], "aInv": null, "rank": null, "MW_proven": null, "gens": null, "gens_reduced": null}]}], "runtime": 16.205397844314575, "exception": false, "timeout": true}