{"label": "137347.a.961429.1", "conductor": 137347, "disc": 961429, "coeffs": [0, 4, 12, 16, 8, 8, 1], "pts": null, "count": null, "root": 0, "g": [[4, 12, 16, 8, 8, 1]], "x-coords": null, "verified": false, "hasse_principle": true, "obstruction_found": false, "search_bound": 100000, "twists": [{"coeffs": ["4", "11", "16", "8", "8", "1"], "found_pts": 1, "base_pt": [1, 0, 0, 0, 0], "loc_solv": true, "pts": null, "verified": false, "g1": [{"g": [4, 12, 16, 8, 8, 1], "aInv": [["0", "0", "0", "0", "0"], ["-32/7", "-352/7", "-53/7", "-395/14", "-27/7"], ["0", "0", "0", "0", "0"], ["-2342/7", "-4993/7", "-1705/7", "-2854/7", "-349/7"], ["-7099/7", "-7004/7", "-3592/7", "-4147/7", "95/14"]], "rank": 1, "MW_proven": true, "gens": [[["187/28", "1021/28", "215/28", "149/7", "81/28"], ["-187/8", "31/8", "-11", "31/16", "1/2"], ["1", "0", "0", "0", "0"]]], "gens_reduced": false, "MW_orders": [0]}]}, {"coeffs": ["1", "-1"], "found_pts": 0, "base_pt": null, "loc_solv": false, "pts": [], "verified": true, "g1": [{"g": [4, 12, 16, 8, 8, 1], "aInv": null, "rank": null, "MW_proven": null, "gens": null, "gens_reduced": null}]}, {"coeffs": ["1"], "found_pts": 2, "base_pt": [0, 0, 0, 0, 1], "loc_solv": true, "pts": null, "verified": false, "g1": [{"g": [4, 12, 16, 8, 8, 1], "aInv": [["0", "0", "0", "0", "0"], ["106/7", "172/7", "85/7", "139/14", "17/14"], ["0", "0", "0", "0", "0"], ["230/7", "479/7", "-57/7", "-3/7", "2/7"], ["379/7", "1117/7", "456/7", "-599/7", "-179/14"]], "rank": 3, "MW_proven": true, "gens": [[["-40/7", "-83/7", "-33/7", "-65/14", "-4/7"], ["-27/7", "-59/7", "-118/7", "-99/14", "-11/14"], ["1", "0", "0", "0", "0"]], [["-2", "-4", "-3", "-15/2", "-1"], ["71/7", "151/7", "127/7", "-99/14", "-9/7"], ["1", "0", "0", "0", "0"]], [["4/7", "-12/7", "39/7", "-53/14", "-9/14"], ["61/7", "83/7", "222/7", "317/14", "18/7"], ["1", "0", "0", "0", "0"]]], "gens_reduced": false, "MW_orders": [0, 0, 0]}]}, {"coeffs": ["4", "11", "17", "8", "8", "1"], "found_pts": 3, "base_pt": [1, 0, 0, 0, 0], "loc_solv": true, "pts": null, "verified": false, "g1": [{"g": [4, 12, 16, 8, 8, 1], "aInv": [["0", "0", "0", "0", "0"], ["-270", "-560", "-199", "-637/2", "-42"], ["0", "0", "0", "0", "0"], ["-2350", "17041", "301", "9468", "1363"], ["425947", "545418", "285411", "316058", "79757/2"]], "rank": null, "MW_proven": null, "gens": null, "gens_reduced": null}]}], "runtime": 82.0754337310791, "exception": false}