{"label": "108126.a.648756.1", "conductor": 108126, "disc": 648756, "coeffs": [0, 8, -27, -10, 51, 42, 9], "pts": null, "count": null, "root": 0, "g": [[8, -27, -10, 51, 42, 9]], "x-coords": [], "verified": false, "hasse_principle": true, "obstruction_found": false, "search_bound": 100000, "twists": [{"coeffs": ["2/3", "-3", "5/3", "11/3", "1"], "found_pts": 2, "base_pt": [-9, -4, 0, -4, 8], "loc_solv": true, "pts": null, "verified": false, "g1": [{"g": [8, -27, -10, 51, 42, 9], "aInv": [["0", "0", "0", "0", "0"], ["-1065", "1911/2", "7281/2", "4509/2", "405"], ["0", "0", "0", "0", "0"], ["-12480", "1953", "44775", "38718", "8910"], ["285768", "-726273/2", "-1731537/2", "-727299/2", "-27702"]], "rank": null, "MW_proven": null, "gens": null, "gens_reduced": null}]}, {"coeffs": ["1"], "found_pts": 1, "base_pt": [0, 0, 0, 0, 1], "loc_solv": true, "pts": null, "verified": false, "g1": [{"g": [8, -27, -10, 51, 42, 9], "aInv": [["0", "0", "0", "0", "0"], ["3387", "-6987/2", "-11874", "-7515", "-2889/2"], ["0", "0", "0", "0", "0"], ["-740640", "624285", "2533347", "1679472", "332694"], ["28847088", "-43630731/2", "-93575043", "-62241075", "-24656643/2"]], "rank": null, "MW_proven": null, "gens": null, "gens_reduced": null}]}, {"coeffs": ["-2/3", "5/3", "1"], "found_pts": 0, "base_pt": null, "loc_solv": false, "pts": [], "verified": true, "g1": [{"g": [8, -27, -10, 51, 42, 9], "aInv": null, "rank": null, "MW_proven": null, "gens": null, "gens_reduced": null}]}, {"coeffs": ["-1", "2", "1"], "found_pts": 3, "base_pt": [-6, -3, 0, -3, 7], "loc_solv": true, "pts": null, "verified": false, "g1": [{"g": [8, -27, -10, 51, 42, 9], "aInv": [["0", "0", "0", "0", "0"], ["-7377", "5871", "49011/2", "32553/2", "6453/2"], ["0", "0", "0", "0", "0"], ["1091232", "-1040763", "-3911643", "-2563047", "-504819"], ["44288784", "-51235443/2", "-130431672", "-88272072", "-35204949/2"]], "rank": null, "MW_proven": null, "gens": null, "gens_reduced": null}]}], "runtime": 13.78858995437622, "exception": false, "timeout": true}