{"label": "436483.a.436483.1", "conductor": 436483, "disc": 436483, "coeffs": [0, 4, 21, -22, -1, 2, 1], "pts": null, "count": null, "root": 0, "g": [[4, 21, -22, -1, 2, 1]], "x-coords": [], "verified": false, "hasse_principle": true, "obstruction_found": false, "search_bound": 100000, "twists": [{"coeffs": ["-4", "-20", "23", "0", "-2", "-1"], "found_pts": 1, "base_pt": [3, 1, 2, 3, 3], "loc_solv": true, "pts": null, "verified": false, "g1": [{"g": [4, 21, -22, -1, 2, 1], "aInv": [["0", "0", "0", "0", "0"], ["-57", "-343", "51", "58", "18"], ["0", "0", "0", "0", "0"], ["3216", "19240", "-3622", "-3642", "-1101"], ["-139016", "-826153", "192607", "170957", "49706"]], "rank": 0, "MW_proven": false, "gens": [], "gens_reduced": true, "MW_orders": [], "Ecov": [[[["-1021519/4096", "3626437/16384", "108131/8192", "-38221/2048", "-332883/32768"], ["132185/32", "-117315/32", "-111935/512", "316523/1024", "86149/512"], ["933/16384", "-18977/65536", "8563/131072", "3719/65536", "2001/131072"]], [[1, 0, 1], [0, 1, 1], [0, 0, 2]]], [[["-2264045/16384", "8037455/65536", "239657/32768", "-84711/8192", "-737785/131072"], ["396555/128", "-351945/128", "-335805/2048", "949569/4096", "258447/2048"], ["719/8192", "-409/8192", "-1179/131072", 0, 0]], [[1, 0, 1], [0, 1, 1], [0, 0, 2]]]]}]}, {"coeffs": ["-1", "-1", "1"], "found_pts": 2, "base_pt": [1, 1, 2, 3, 7], "loc_solv": true, "pts": null, "verified": false, "g1": [{"g": [4, 21, -22, -1, 2, 1], "aInv": [["0", "0", "0", "0", "0"], ["1523", "-1351", "-81", "114", "62"], ["0", "0", "0", "0", "0"], ["-2644136", "2346922", "139672", "-197812", "-107685"], ["832451984", "-738810655", "-44051909", "62289973", "33908428"]], "rank": null, "MW_proven": null, "gens": null, "gens_reduced": null, "Ecov": [[[["65251/83521", "767153/167042", "-13873/9826", "-10809/9826", "-51503/167042"], ["1201/4913", "14805/9826", "81/4913", "-730/4913", "-563/9826"], ["-1478/83521", "-1372/83521", "-2897/167042", "-451/83521", "-7/83521"]], [[1, 0, 1], [0, 1, 1], [0, 0, 2]]], [[["-15732/83521", "-92333/83521", "1733/4913", "1329/4913", "6297/83521"], ["2402/4913", "14805/4913", "162/4913", "-1460/4913", "-563/4913"], ["-208/83521", "1068/83521", "571/167042", 0, 0]], [[1, 0, 1], [0, 1, 1], [0, 0, 2]]]]}]}, {"coeffs": ["1"], "found_pts": 1, "base_pt": [0, 0, 0, 0, 1], "loc_solv": true, "pts": null, "verified": false, "g1": [{"g": [4, 21, -22, -1, 2, 1], "aInv": [["0", "0", "0", "0", "0"], ["-1", "-7", "5", "0", "0"], ["0", "0", "0", "0", "0"], ["1184", "6596", "-4796", "-3748", "2465"], ["288568", "1614103", "-1137075", "-964517", "618832"]], "rank": null, "MW_proven": null, "gens": null, "gens_reduced": null, "Ecov": [[[[-10, -77, "43/2", "35/2", 5], ["-11/4", "-257/16", "-61/32", "15/16", "21/32"]], [[1, 0, 1], [0, 0, 2]]], [[["77/4", "1751/16", "-1023/32", "-815/32", "-115/16"], [19, "495/4", "-497/16", "-425/16", "-123/16"], ["1/2", "13/4", "29/32", 0, 0]], [[1, 0, 1], [0, 1, 1], [0, 0, 2]]]]}]}, {"coeffs": ["4", "20", "-22", "-1", "2", "1"], "found_pts": 1, "base_pt": [1, 0, 0, 0, 0], "loc_solv": true, "pts": null, "verified": false, "g1": [{"g": [4, 21, -22, -1, 2, 1], "aInv": [["0", "0", "0", "0", "0"], ["11", "5", "1", "0", "0"], ["0", "0", "0", "0", "0"], ["-88", "102", "22", "-2", "-3"], ["208", "97", "-3", "-9", "-2"]], "rank": null, "MW_proven": null, "gens": null, "gens_reduced": null, "Ecov": [[[[-1, "-1/2", 0, 0, 0], [1, 0, 0, 0, 0], [18, -2, "-5/2", -1, 0]], [[1, 0, 1], [0, 1, 1], [0, 0, 2]]], [[[2, 0, 0, 0, 0], [4, 4, "3/2", 0, 0]], [[1, 0, 1], [0, 0, 2]]]]}]}], "runtime": 92.927663564682, "exception": false, "timeout": true}